prestashop_api.py
prestashop_api-0.0.1b1.dist-info/DESCRIPTION.rst
prestashop_api-0.0.1b1.dist-info/METADATA
prestashop_api-0.0.1b1.dist-info/RECORD
prestashop_api-0.0.1b1.dist-info/WHEEL
prestashop_api-0.0.1b1.dist-info/metadata.json
prestashop_api-0.0.1b1.dist-info/top_level.txt
