Metadata-Version: 2.0
Name: prestashop-api
Version: 0.0.1b1
Summary: Prestashop api wrapper for python
Home-page: https://github.com/savaskoc/prestashop_api
Author: Savas Koc
Author-email: savaskoc11@gmail.com
License: Apache License 2.0
Keywords: prestashop api
Platform: UNKNOWN
Classifier: Development Status :: 4 - Beta
Classifier: Intended Audience :: Developers
Classifier: Topic :: Software Development :: Libraries
Classifier: License :: OSI Approved :: Apache Software License
Classifier: Programming Language :: Python :: 2
Classifier: Programming Language :: Python :: 3
Requires-Dist: requests
Requires-Dist: xmltodict
